{"dependencies":[{"name":"./css/styles.scss","dynamic":true},{"name":"./js/scripts.js","dynamic":true},{"name":"./genius.html","dynamic":true,"entry":true}],"generated":{"html":"<!DOCTYPE html>\n<html>\n<head>\n  <meta charset=\"utf-8\">\n  <meta http-equiv=\"X-UA-Compatible\" content=\"IE=edge\">\n  <title>Page Title</title>\n  <meta name=\"viewport\" content=\"width=device-width, initial-scale=1\">\n  <link rel=\"stylesheet\" type=\"text/css\" media=\"screen\" href=\"/263cdebb7c5f9aabea015f1d1594159a.css\">\n  <script src=\"/8c5571ac4da4be79ab91b23979b960f8.js\"></script>\n</head>\n<body>\n  <h1> ALYSSA WAS HERE</h1>\n  <a href=\"/5167904eeebc7794c102d187eed5b6f3.html\">click for genius</a>\n</body>\n</html>"},"hash":"1f622f62e6871fc8362b21a1d3ac95b7","cacheData":{}}